urpautils/__about__.py
urpautils/__init__.py
urpautils/csv_utils.py
urpautils/file_utils.py
urpautils/py.typed
urpautils/robot.py
urpautils/universal.py
urpautils-0.10.1.dist-info/LICENSE
urpautils-0.10.1.dist-info/METADATA
urpautils-0.10.1.dist-info/WHEEL
urpautils-0.10.1.dist-info/top_level.txt
urpautils-0.10.1.dist-info/RECORD
