Metadata-Version: 2.1
Name: urpautils
Version: 0.10.1
Summary: Module containig universal functions used with UltimateRPA robots
Home-page: https://github.com/ultimaterpa/urpautils
Author: anerold
Author-email: support@ultimaterpa.cz
License: MIT
Keywords: Robotic Process Automation,RPA,UltimateRPA,utilities
Platform: UNKNOWN
Classifier: Intended Audience :: Developers
Classifier: Programming Language :: Python :: 3.7
Classifier: Operating System :: Microsoft :: Windows
Classifier: License :: OSI Approved :: MIT License
Requires-Python: >=3.7
Requires-Dist: urpatimeout
Requires-Dist: holidays
